odoo/addons/ssi_transaction_confirm_mixin/README.rst
odoo/addons/ssi_transaction_confirm_mixin/__init__.py
odoo/addons/ssi_transaction_confirm_mixin/__manifest__.py
odoo/addons/ssi_transaction_confirm_mixin/i18n/ssi_transaction_confirm_mixin.pot
odoo/addons/ssi_transaction_confirm_mixin/models/__init__.py
odoo/addons/ssi_transaction_confirm_mixin/models/mixin_transaction_confirm.py
odoo/addons/ssi_transaction_confirm_mixin/static/description/icon.png
odoo/addons/ssi_transaction_confirm_mixin/templates/mixin_transaction_confirm_templates.xml
odoo14_addon_ssi_transaction_confirm_mixin-14.0.2.10.1.dist-info/METADATA
odoo14_addon_ssi_transaction_confirm_mixin-14.0.2.10.1.dist-info/WHEEL
odoo14_addon_ssi_transaction_confirm_mixin-14.0.2.10.1.dist-info/top_level.txt
odoo14_addon_ssi_transaction_confirm_mixin-14.0.2.10.1.dist-info/RECORD
